anndata_mcp/__init__.py
anndata_mcp/main.py
anndata_mcp/mcp.py
anndata_mcp/tools/__init__.py
anndata_mcp/tools/_exploration.py
anndata_mcp/tools/_file_system.py
anndata_mcp/tools/_summary.py
anndata_mcp/tools/_view.py
anndata_mcp/tools/utils.py
anndata_mcp-0.2.10.dist-info/METADATA
anndata_mcp-0.2.10.dist-info/WHEEL
anndata_mcp-0.2.10.dist-info/entry_points.txt
anndata_mcp-0.2.10.dist-info/licenses/LICENSE
anndata_mcp-0.2.10.dist-info/RECORD
