Metadata-Version: 2.4
Name: anndata-mcp
Version: 0.2.10
Summary: Allows to retrieve information about an AnnData object via MCP
Project-URL: Documentation, https://anndata-mcp.readthedocs.io/
Project-URL: Homepage, https://github.com/biocontext-ai/anndata-mcp
Project-URL: Source, https://github.com/biocontext-ai/anndata-mcp
Author: Darius Schaub, Malte Kuehl
Maintainer-email: Darius Schaub <schaub.darius@gmail.com>, Malte Kuehl <malte.kuehl@clin.au.dk>
License: 
License-File: LICENSE
Classifier: Programming Language :: Python :: 3 :: Only
Classifier: Programming Language :: Python :: 3.11
Classifier: Programming Language :: Python :: 3.12
Classifier: Programming Language :: Python :: 3.13
Requires-Python: <3.14,>=3.11
Requires-Dist: aiohttp>=3.13.2
Requires-Dist: anndata>=0.12.6
Requires-Dist: click
Requires-Dist: dask>=2025.9.1
Requires-Dist: fastmcp
Requires-Dist: httpx<1
Requires-Dist: pandas<3
Requires-Dist: xarray>=2025.9
Provides-Extra: dev
Requires-Dist: jupyter; extra == 'dev'
Requires-Dist: pre-commit; extra == 'dev'
Requires-Dist: ruff; extra == 'dev'
Requires-Dist: scanpy; extra == 'dev'
Requires-Dist: session-info2; extra == 'dev'
Requires-Dist: twine>=4.0.2; extra == 'dev'
Provides-Extra: doc
Requires-Dist: docutils!=0.18.*,!=0.19.*,>=0.8; extra == 'doc'
Requires-Dist: ipykernel; extra == 'doc'
Requires-Dist: ipython; extra == 'doc'
Requires-Dist: myst-nb>=1.1; extra == 'doc'
Requires-Dist: pandas; extra == 'doc'
Requires-Dist: setuptools; extra == 'doc'
Requires-Dist: sphinx-autoapi; extra == 'doc'
Requires-Dist: sphinx-book-theme>=1; extra == 'doc'
Requires-Dist: sphinx-copybutton; extra == 'doc'
Requires-Dist: sphinx-tabs; extra == 'doc'
Requires-Dist: sphinx>=8.1; extra == 'doc'
Requires-Dist: sphinxext-opengraph; extra == 'doc'
Provides-Extra: test
Requires-Dist: coverage; extra == 'test'
Requires-Dist: pytest; extra == 'test'
Requires-Dist: pytest-asyncio; extra == 'test'
